noize/__init__.py
noize/__main__.py
noize/cmd.py
noize/noise.py
noize/util.py
tests/__init__.py
tests/test_noise.py
tests/test_util.py
noize-0.0.1.dist-info/LICENSE
noize-0.0.1.dist-info/METADATA
noize-0.0.1.dist-info/WHEEL
noize-0.0.1.dist-info/entry_points.txt
noize-0.0.1.dist-info/top_level.txt
noize-0.0.1.dist-info/RECORD
