Metadata-Version: 2.1
Name: noize
Version: 0.0.1
Summary: A small library and a cli tool for applying noise to images.
Home-page: https://github.com/mcemilg/noize
Author: MCG
Author-email: mcemilguneyy@gmail.com
License: MIT
Platform: UNKNOWN
Classifier: License :: OSI Approved :: MIT License
Classifier: Programming Language :: Python :: 3
Classifier: Programming Language :: Python :: 3.8
License-File: LICENSE
Requires-Dist: numpy (==1.19.4)
Requires-Dist: Pillow (==8.0.1)
